setuptools_reproducible.py
setuptools_reproducible-0.1.dist-info/LICENSE
setuptools_reproducible-0.1.dist-info/METADATA
setuptools_reproducible-0.1.dist-info/WHEEL
setuptools_reproducible-0.1.dist-info/top_level.txt
setuptools_reproducible-0.1.dist-info/RECORD
