Metadata-Version: 2.1
Name: setuptools-reproducible
Version: 0.1
Summary: Extension of setuptools to support reproducible dists
Author: Wim Jeantine-Glenn
Author-email: hey@wimglenn.com
License: MIT
Project-URL: Homepage, https://github.com/wimglenn/setuptools-reproducible
Requires-Python: >=3.8
License-File: LICENSE
Requires-Dist: setuptools
